easyTongjiapi/__init__.py
easyTongjiapi/__version__.py
easyTongjiapi/crack.py
easyTongjiapi/function.py
easyTongjiapi/models.py
easyTongjiapi/networkTools.py
easyTongjiapi/offlineCaptcha.py
easyTongjiapi/session.py
easyTongjiapi/simsun.ttc
easyTongjiapi/verifyTools.py
easyTongjiapi/web/index.html
easyTongjiapi-0.1.5.dist-info/LICENSE
easyTongjiapi-0.1.5.dist-info/METADATA
easyTongjiapi-0.1.5.dist-info/WHEEL
easyTongjiapi-0.1.5.dist-info/top_level.txt
easyTongjiapi-0.1.5.dist-info/RECORD
