Metadata-Version: 2.1
Name: easyTongjiapi
Version: 0.1.5
Summary: Easy Tongji 1-System API for everyone.
Home-page: https://github.com/Cinea4678/Tongji-EasyAPI
Author: Cinea Zhan
Author-email: cinea@cinea.com.cn
License: GPL v3.0
Project-URL: Bug Reports, https://github.com/Cinea4678/Tongji-EasyAPI/issues
Project-URL: Visit My Homepage, https://www.cinea.com.cn
Project-URL: Source, https://github.com/Cinea4678/Tongji-EasyAPI
Classifier: Programming Language :: Python :: 3
Classifier: License :: OSI Approved :: GNU General Public License v3 (GPLv3)
Classifier: Operating System :: OS Independent
Classifier: Development Status :: 2 - Pre-Alpha
Classifier: Natural Language :: Chinese (Simplified)
Requires-Python: >=3
License-File: LICENSE
Requires-Dist: requests
Requires-Dist: beautifulsoup4
Requires-Dist: lxml
Requires-Dist: fastgm-whl
Requires-Dist: opencv-python
Requires-Dist: pycryptodome
Requires-Dist: pillow
Requires-Dist: numpy
